pyworkforce/__init__.py
pyworkforce/_version.py
pyworkforce/queuing/__init__.py
pyworkforce/queuing/erlang.py
pyworkforce/queuing/tests/__init__.py
pyworkforce/queuing/tests/test_erlang.py
pyworkforce/queuing/tests/test_multi_erlang.py
pyworkforce/rostering/__init__.py
pyworkforce/rostering/binary_programming.py
pyworkforce/rostering/tests/__init__.py
pyworkforce/rostering/tests/test_rostering.py
pyworkforce/scheduling/__init__.py
pyworkforce/scheduling/base.py
pyworkforce/scheduling/shifts_selection.py
pyworkforce/scheduling/utils.py
pyworkforce/scheduling/tests/__init__.py
pyworkforce/scheduling/tests/test_shifts.py
pyworkforce/scheduling/tests/test_utils.py
pyworkforce/utils/__init__.py
pyworkforce/utils/grid.py
pyworkforce/utils/tests/__init__.py
pyworkforce/utils/tests/test_parameter_grid.py
pyworkforce-0.5.1.dist-info/LICENSE
pyworkforce-0.5.1.dist-info/METADATA
pyworkforce-0.5.1.dist-info/WHEEL
pyworkforce-0.5.1.dist-info/top_level.txt
pyworkforce-0.5.1.dist-info/RECORD
