Metadata-Version: 2.1
Name: pyworkforce
Version: 0.5.1
Summary: Common tools for workforce management, schedule and optimization problems
Home-page: https://github.com/rodrigo-arenas/pyworkforce
Author: Rodrigo Arenas
Author-email: rodrigo.arenas456@gmail.com
License: MIT
Project-URL: Documentation, https://pyworkforce.readthedocs.io/en/stable/
Project-URL: Source Code, https://github.com/rodrigo-arenas/pyworkforce
Project-URL: Bug Tracker, https://github.com/rodrigo-arenas/pyworkforce/issues
Classifier: License :: OSI Approved :: MIT License
Classifier: Programming Language :: Python :: 3
Classifier: Programming Language :: Python :: 3.8
Classifier: Programming Language :: Python :: 3.9
Classifier: Programming Language :: Python :: 3.10
Classifier: Programming Language :: Python :: 3.11
Requires-Python: >=3.8
License-File: LICENSE
Requires-Dist: numpy (>=1.23.0)
Requires-Dist: ortools (>=9.2.9972)
Requires-Dist: pandas (>=1.3.5)
Requires-Dist: joblib (>0.17)
